{"body":"### Option Pricing with Python \r\n\r\nFame isn't all  \r\n***\r\n\r\nThe Black-Sholes-Merton model is very popular but that model isn't actually being used by options traders . In fact,  they mostly use a heuristically derived pricing formula which is then adapted by varying the standard deviation of a Gaussian. \r\nStudying the in and outs of the Black Scholes Model isn't without interest though . \r\n\r\nEuropean Vanilla Calls and Puts\r\n***\r\nThe Black Sholes formula is mainly applied for the pricing of European Vanilla Calls and Puts.\r\nThe price of a European Vanilla Call, C(S,t) is going to be described below.\r\nS being the underlying asset , K the strike price, r the risk-free rate, T the time to maturity, and  \r\nsigma the constant volatility of the underlying asset.\r\n      \r\n\r\n            C(S,t) = SN(d_1) - Ke^{-rT} N(d_2)\r\nd1 and d2 being by :\r\n```\r\n\r\n```\r\n\r\n\r\n### Authors and Contributors\r\n\r\nBrennanMulwray\r\n","note":"Don't delete this file! It's used internally to help with page regeneration.","google":"BrennanMulwray","name":"Quantitative Finances","tagline":""}